{"repo": {"timestamp": 1778160171000, "version": 20002, "name": "Cacing69 Repository", "icon": "icon.png", "address": "https://cacing69.github.io/f-droid/repo", "description": "Personal F-Droid repository for experimental and production Android apps."}, "requests": {"install": [], "uninstall": []}, "apps": [{"categories": ["Internet", "Development", "Security"], "suggestedVersionCode": "14010", "description": "A lightweight curl client for sending HTTP requests and inspecting responses with syntax highlighting.", "issueTracker": "https://github.com/cacing69/curel/issues", "license": "Unknown", "name": "Curel", "sourceCode": "https://github.com/cacing69/curel", "summary": "cUrl client", "webSite": "https://cacing69.github.io/", "added": 1778160170000, "packageName": "dev.cacing69.curel", "lastUpdated": 1778160171000, "localized": {"en-US": {"icon": "icon_w0jtqtRGqNDN7PRM8L0GOr42uYcFqzO_2kuWrbwt24I=.png", "phoneScreenshots": ["01.jpeg", "02.jpeg", "03.jpeg", "04.jpeg"]}}}], "packages": {"dev.cacing69.curel": [{"added": 1778160171000, "apkName": "dev.cacing69.curel-x86_64.apk", "hash": "523235fcaa042abb1da6c65c912adaf74339ab3a9367e9fa6d00e508675ecff1", "hashType": "sha256", "minSdkVersion": 24, "nativecode": ["x86_64"], "packageName": "dev.cacing69.curel", "sig": "4de904f847a9c4421e0a4af61334925b", "signer": "251b142020e72938df647f22a373b93d9240ba3cbcd232f86772ad9007564a44", "size": 22211845, "targetSdkVersion": 36, "uses-permission": [["android.permission.INTERNET", null], ["dev.cacing69.curel.DYNAMIC_RECEIVER_NOT_EXPORTED_PERMISSION", null]], "versionCode": 14010, "versionName": "1.0.10"}, {"added": 1778160170000, "apkName": "dev.cacing69.curel-arm64-v8a.apk", "hash": "28922b151c67f628e60dd82ca1d5aa2629c0cccea67ca02aecea36ad3dfdb4c6", "hashType": "sha256", "minSdkVersion": 24, "nativecode": ["arm64-v8a"], "packageName": "dev.cacing69.curel", "sig": "4de904f847a9c4421e0a4af61334925b", "signer": "251b142020e72938df647f22a373b93d9240ba3cbcd232f86772ad9007564a44", "size": 20833966, "targetSdkVersion": 36, "uses-permission": [["android.permission.INTERNET", null], ["dev.cacing69.curel.DYNAMIC_RECEIVER_NOT_EXPORTED_PERMISSION", null]], "versionCode": 12010, "versionName": "1.0.10"}, {"added": 1778160171000, "apkName": "dev.cacing69.curel-armeabi-v7a.apk", "hash": "9089c528ae4e54704d6a7fd5fdf767d87d2cfe600baa33c29bf321ee322f11e0", "hashType": "sha256", "minSdkVersion": 24, "nativecode": ["armeabi-v7a"], "packageName": "dev.cacing69.curel", "sig": "4de904f847a9c4421e0a4af61334925b", "signer": "251b142020e72938df647f22a373b93d9240ba3cbcd232f86772ad9007564a44", "size": 18497240, "targetSdkVersion": 36, "uses-permission": [["android.permission.INTERNET", null], ["dev.cacing69.curel.DYNAMIC_RECEIVER_NOT_EXPORTED_PERMISSION", null]], "versionCode": 11010, "versionName": "1.0.10"}]}}